runtracker/__init__.py
runtracker/cli.py
runtracked-0.1.0.dist-info/METADATA
runtracked-0.1.0.dist-info/WHEEL
runtracked-0.1.0.dist-info/entry_points.txt
runtracked-0.1.0.dist-info/top_level.txt
runtracked-0.1.0.dist-info/RECORD
