Metadata-Version: 2.4
Name: runtracked
Version: 0.1.0
Summary: A terminal-based running tracker with CSV logging and ASCII line charts
Author-email: Eren Öğrül <termapp@pm.me>
License: MIT
Requires-Python: >=3.8
